simpletask/__init__.py
simpletask/persistence.py
simpletask/scheduler.py
simpletask-1.0.2.dist-info/LICENSE
simpletask-1.0.2.dist-info/METADATA
simpletask-1.0.2.dist-info/WHEEL
simpletask-1.0.2.dist-info/top_level.txt
simpletask-1.0.2.dist-info/RECORD
